{
  "schema_version": "flaggems_active_batch_v1",
  "generated_at": "2026-02-14T04:39:53+00:00",
  "branch": "flaggems",
  "batch_size": 10,
  "selection_policy": [
    "blocked_ir",
    "missing_e2e_spec",
    "backend_missing_ops"
  ],
  "items": [
    {
      "id": "flaggems::softplus",
      "semantic_op": "softplus",
      "family": "norm_activation",
      "status": "blocked_backend",
      "passes": false,
      "reason_code": "missing_e2e_spec",
      "next_action": "add_e2e_spec",
      "e2e_spec": null,
      "intent_ops": [
        "exp",
        "add",
        "log"
      ]
    },
    {
      "id": "flaggems::sort",
      "semantic_op": "sort",
      "family": "elementwise_broadcast",
      "status": "blocked_backend",
      "passes": false,
      "reason_code": "missing_e2e_spec",
      "next_action": "add_e2e_spec",
      "e2e_spec": null,
      "intent_ops": [
        "sort"
      ]
    },
    {
      "id": "flaggems::sort_stable",
      "semantic_op": "sort_stable",
      "family": "elementwise_broadcast",
      "status": "blocked_backend",
      "passes": false,
      "reason_code": "missing_e2e_spec",
      "next_action": "add_e2e_spec",
      "e2e_spec": null,
      "intent_ops": [
        "sort"
      ]
    },
    {
      "id": "flaggems::stack",
      "semantic_op": "stack",
      "family": "elementwise_broadcast",
      "status": "blocked_backend",
      "passes": false,
      "reason_code": "missing_e2e_spec",
      "next_action": "add_e2e_spec",
      "e2e_spec": null,
      "intent_ops": [
        "stack"
      ]
    },
    {
      "id": "flaggems::std",
      "semantic_op": "std",
      "family": "reduction",
      "status": "blocked_backend",
      "passes": false,
      "reason_code": "missing_e2e_spec",
      "next_action": "add_e2e_spec",
      "e2e_spec": null,
      "intent_ops": [
        "std"
      ]
    },
    {
      "id": "flaggems::tan",
      "semantic_op": "tan",
      "family": "elementwise_broadcast",
      "status": "blocked_backend",
      "passes": false,
      "reason_code": "missing_e2e_spec",
      "next_action": "add_e2e_spec",
      "e2e_spec": null,
      "intent_ops": [
        "tan"
      ]
    },
    {
      "id": "flaggems::tile",
      "semantic_op": "tile",
      "family": "elementwise_broadcast",
      "status": "blocked_backend",
      "passes": false,
      "reason_code": "missing_e2e_spec",
      "next_action": "add_e2e_spec",
      "e2e_spec": null,
      "intent_ops": [
        "tile"
      ]
    },
    {
      "id": "flaggems::topk",
      "semantic_op": "topk",
      "family": "elementwise_broadcast",
      "status": "blocked_backend",
      "passes": false,
      "reason_code": "missing_e2e_spec",
      "next_action": "add_e2e_spec",
      "e2e_spec": null,
      "intent_ops": [
        "topk"
      ]
    },
    {
      "id": "flaggems::var_mean",
      "semantic_op": "var_mean",
      "family": "reduction",
      "status": "blocked_backend",
      "passes": false,
      "reason_code": "missing_e2e_spec",
      "next_action": "add_e2e_spec",
      "e2e_spec": null,
      "intent_ops": [
        "var",
        "mean"
      ]
    },
    {
      "id": "flaggems::vector_norm",
      "semantic_op": "vector_norm",
      "family": "norm_activation",
      "status": "blocked_backend",
      "passes": false,
      "reason_code": "missing_e2e_spec",
      "next_action": "add_e2e_spec",
      "e2e_spec": null,
      "intent_ops": [
        "mul",
        "reduce_sum",
        "sqrt"
      ]
    }
  ],
  "context": {
    "feature_list_path": "workflow/flaggems/state/feature_list.json",
    "progress_log_path": "workflow/flaggems/state/progress_log.jsonl",
    "git_log": "ac146f2 workflow: record log-min-pad batch and plan next backend wave\n8052234 flaggems: add log-min-pad batch specs and baseline aliases\nbcee88f workflow: record active-batch backend wave and plan next blocked-backend queue\n3f02af3 flaggems: add active-batch specs and enable rvv/cuda cos-erf lowering\nc71f7da workflow: record blocked-ir-zero wave and refresh next batch\nf6f618a intentir: clear remaining blocked_ir with attention/unique/weightnorm mappings\n381e75b workflow: refresh active batch after scatter-quantile-polar wave\n874e0a9 workflow: record scatter-quantile-polar wave and refresh queue\n3583f1b intentir: map scatter family plus quantile and polar into flaggems flow\n9a8c184 workflow: refresh active batch context after trace-triu-upsample wave\nebc9011 workflow: record trace-triu-upsample batch and refresh queue\n6b1f134 intentir: expand flaggems mapping with conv and nearest/trace/triu ops\ne778320 workflow: record one-hot/nll-forward/maxpool batch and replan queue\n4e5cf1b intentir: add one_hot/nll_loss_forward/max_pool2d_with_indices wave\n3f75bed workflow: finalize handoff for masked-select/mse/nan-to-num/nll wave\n32bbc88 workflow: record masked-select/mse/nan-to-num/nll batch and refresh queue\n7169c84 intentir: add masked_select/mse_loss/nan_to_num/nll_loss2d_forward wave\n69610df workflow: finalize handoff for isin-kron-linspace-logspace-masked_scatter wave\nc8e7240 workflow: record isin-kron-linspace-logspace-masked_scatter batch and replan queue\n643e46e flaggems: add isin/kron/linspace/logspace/masked_scatter wave and scoped matrix convergence",
    "progress_tail": [
      "{\"ts\": \"2026-02-14T00:18:57+00:00\", \"commit\": \"3583f1b\", \"summary\": \"Mapped scatter/select_scatter/slice_scatter/quantile/polar into IntentIR with deterministic specs and multibackend classification.\", \"batch_ops\": [\"scatter\", \"select_scatter\", \"slice_scatter\", \"quantile\", \"polar\"], \"active_batch_path\": \"artifacts/flaggems_matrix/daily/20260214/batch_scatter_quantile_polar_v2/active_batch_scatter_quantile_polar.json\", \"run_summary_path\": \"artifacts/flaggems_matrix/daily/20260214/batch_scatter_quantile_polar_v2/run_summary.json\", \"status_converged_path\": \"artifacts/flaggems_matrix/daily/20260214/batch_scatter_quantile_polar_v2/status_converged.json\", \"next_focus\": \"Drive remaining blocked_ir queue (attention/per_token/unique2/weight_norm), then backend-lowering for scatter/quantile/polar family.\", \"run_ok\": false, \"run_out_dir\": \"artifacts/flaggems_matrix/daily/20260214/batch_scatter_quantile_polar_v2\", \"counts_by_status\": {\"blocked_backend\": 189, \"blocked_ir\": 7}}",
      "{\"ts\": \"2026-02-14T00:47:10+00:00\", \"commit\": \"f6f618a\", \"summary\": \"Cleared remaining blocked_ir by mapping unique2/weight_norm_interface/SDPA family and added deterministic specs with RVV/CUDA classified blockers.\", \"batch_ops\": [\"unique2\", \"weight_norm_interface\", \"scaled_dot_product_attention\"], \"active_batch_path\": \"artifacts/flaggems_matrix/daily/20260214/batch_attention_unique_weightnorm_v3_combined/active_batch_attention_unique_weightnorm.json\", \"run_summary_path\": \"artifacts/flaggems_matrix/daily/20260214/batch_attention_unique_weightnorm_v3_combined/run_summary.json\", \"status_converged_path\": \"artifacts/flaggems_matrix/daily/20260214/batch_attention_unique_weightnorm_v3_combined/status_converged.json\", \"next_focus\": \"1) Fix unique2 and scaled_dot_product_attention diff_fail in pipeline. 2) Implement RVV/CUDA lowering for unique/weight_norm_interface/scaled_dot_product_attention. 3) Continue next planned backend_missing batch from active_batch.json.\", \"run_ok\": false, \"run_out_dir\": \"artifacts/flaggems_matrix/daily/20260214/batch_attention_unique_weightnorm_v3_combined\", \"counts_by_status\": {\"blocked_backend\": 196}}",
      "{\"ts\": \"2026-02-14T01:35:29+00:00\", \"commit\": \"c71f7da0a51e0c9ec9928ba742120916e6a83562\", \"summary\": \"Completed active-batch backend wave for argmax/argmin/pad/conv2d/cos/cumsum/erf/flash/gelu/hstack with scoped RVV local+remote and CUDA subset evidence.\", \"batch_ops\": [\"argmax\", \"argmin\", \"constant_pad_nd\", \"conv2d\", \"cos\", \"cumsum\", \"erf\", \"flash_attn_varlen_func\", \"gelu\", \"hstack\"], \"active_batch_path\": \"artifacts/flaggems_matrix/daily/20260214/batch_active10_backend_wave_v3/active_batch_completed.json\", \"run_summary_path\": \"artifacts/flaggems_matrix/daily/20260214/batch_active10_backend_wave_v3/run_summary.json\", \"status_converged_path\": \"artifacts/flaggems_matrix/daily/20260214/batch_active10_backend_wave_v3/status_converged.json\", \"next_focus\": \"1) Fix baseline I/O aliasing for argmax/argmin/constant_pad_nd/hstack/flash specs. 2) Add RVV gelu path shape inference for erf intermediate. 3) Stabilize CUDA smoke timeout behavior and rerun full 10-kernel gate.\", \"run_ok\": false, \"run_out_dir\": \"artifacts/flaggems_matrix/daily/20260214/batch_active10_backend_wave_v3\", \"counts_by_status\": {\"blocked_backend\": 194, \"rvv_only\": 2}}",
      "{\"ts\": \"2026-02-14T02:08:52+00:00\", \"commit\": \"8052234\", \"summary\": \"Added e2e specs for log/min/nonzero/normed_cumsum/pad/per_token_group_quant_fp8/pow_scalar wave and validated pipeline+rvv local/remote+cuda classification.\", \"batch_ops\": [\"log\", \"log_sigmoid\", \"log_softmax\", \"min\", \"min_dim\", \"nonzero\", \"normed_cumsum\", \"pad\", \"per_token_group_quant_fp8\", \"pow_scalar\"], \"active_batch_path\": \"workflow/flaggems/state/active_batch.json\", \"run_summary_path\": \"artifacts/flaggems_matrix/daily/20260214/batch_active10_log_min_pad_v1/run_summary.json\", \"status_converged_path\": \"artifacts/flaggems_matrix/daily/20260214/batch_active10_log_min_pad_v1/status_converged.json\", \"next_focus\": \"1) Eliminate remaining baseline alias mismatches for min/nonzero/pad/per_token outputs. 2) Add RVV/CUDA lowering for log/reduce_min/pow/cumsum/nonzero/pad primitives. 3) Re-run scoped batch gate, then plan next blocked-backend batch.\", \"run_ok\": true, \"run_out_dir\": \"artifacts/flaggems_matrix/daily/20260214/batch_active10_log_min_pad_v1\", \"counts_by_status\": {\"blocked_backend\": 196}}",
      "{\"ts\": \"2026-02-14T04:38:43+00:00\", \"commit\": \"ac146f2074508c6041cb3a67b3168ab886c7d427\", \"summary\": \"Added pow/prod/remainder/repeat/sin batch e2e specs and ran scoped RVV local+remote+CUDA convergence.\", \"batch_ops\": [\"pow_tensor_scalar\", \"pow_tensor_tensor\", \"prod\", \"prod_dim\", \"remainder\", \"repeat\", \"repeat_interleave_self_int\", \"repeat_interleave_self_tensor\", \"repeat_interleave_tensor\", \"sin\"], \"active_batch_path\": \"workflow/flaggems/state/active_batch.json\", \"run_summary_path\": \"artifacts/flaggems_matrix/daily/20260214/batch_active10_pow_prod_repeat_v1/run_summary.json\", \"status_converged_path\": \"artifacts/flaggems_matrix/daily/20260214/batch_active10_pow_prod_repeat_v1/status_converged.json\", \"next_focus\": \"1) implement RVV/CUDA lowering for pow/reduce_prod/sin; 2) fix baseline alias/runtime issues for repeat/repeat_interleave; 3) plan next backend_missing_ops batch.\", \"run_ok\": true, \"run_out_dir\": \"artifacts/flaggems_matrix/daily/20260214/batch_active10_pow_prod_repeat_v1\", \"counts_by_status\": {\"blocked_backend\": 196}}"
    ]
  }
}